pyflowchart/__init__.py
pyflowchart/__main__.py
pyflowchart/ast_node.py
pyflowchart/flowchart.py
pyflowchart/node.py
pyflowchart/output_html.py
pyflowchart/test.py
pyflowchart-0.3.1.dist-info/LICENSE
pyflowchart-0.3.1.dist-info/METADATA
pyflowchart-0.3.1.dist-info/WHEEL
pyflowchart-0.3.1.dist-info/top_level.txt
pyflowchart-0.3.1.dist-info/RECORD
