Metadata-Version: 2.1
Name: pyflowchart
Version: 0.3.1
Summary: Python codes to Flowcharts.
Home-page: https://github.com/cdfmlr/pyflowchart
Author: CDFMLR
Author-email: cdfmlr@outlook.com
License: MIT
Classifier: Development Status :: 3 - Alpha
Classifier: Environment :: Console
Classifier: License :: OSI Approved :: MIT License
Classifier: Programming Language :: Python :: 3
Classifier: Topic :: Software Development :: Code Generators
Classifier: Topic :: Utilities
Requires-Python: >=3.6
License-File: LICENSE
